apic0nnect0r/__init__.py
apic0nnect0r/code_data.py
apic0nnect0r-1.0.0.dist-info/METADATA
apic0nnect0r-1.0.0.dist-info/WHEEL
apic0nnect0r-1.0.0.dist-info/RECORD
