Metadata-Version: 2.4
Name: apic0nnect0r
Version: 1.0.0
Summary: api connector
Author-email: You <dev@example.com>
Requires-Python: >=3.11
Requires-Dist: pygments>=2.15.0
